pyobjectscript_gen/__init__.py
pyobjectscript_gen/cls.py
pyobjectscript_gen/templates/class.cls.jinja
pyobjectscript_gen/templates/docstring.cls.jinja
pyobjectscript_gen/templates/foreignkey.cls.jinja
pyobjectscript_gen/templates/index.cls.jinja
pyobjectscript_gen/templates/keywords.cls.jinja
pyobjectscript_gen/templates/method.cls.jinja
pyobjectscript_gen/templates/parameter.cls.jinja
pyobjectscript_gen/templates/projection.cls.jinja
pyobjectscript_gen/templates/property.cls.jinja
pyobjectscript_gen/templates/query.cls.jinja
pyobjectscript_gen/templates/storage.cls.jinja
pyobjectscript_gen/templates/trigger.cls.jinja
pyobjectscript_gen/templates/xdata.cls.jinja
pyobjectscript_gen-1.0.dist-info/METADATA
pyobjectscript_gen-1.0.dist-info/WHEEL
pyobjectscript_gen-1.0.dist-info/RECORD
