Metadata-Version: 2.4
Name: pyobjectscript_gen
Version: 1.0
Summary: Objectscript class code generation library for Python
Project-URL: Documentation, https://readthedocs.org
Project-URL: Repository, https://github.com/Antoine-dh/pyobjectscript_gen.git
Project-URL: Bug Tracker, https://github.com/Antoine-dh/pyobjectscript_gen/issues
Project-URL: Changelog, https://github.com/Antoine-dh/pyobjectscript_gen/blob/master/CHANGELOG.md
Author: Antoine-dh
Maintainer: Antoine-dh
License-Expression: GPL-3.0
Keywords: cls,code generation,intersystems,iris,objectscript
Classifier: Development Status :: 4 - Beta
Classifier: Intended Audience :: Developers
Classifier: Programming Language :: Python :: 3.9
Classifier: Topic :: Software Development :: Libraries
Requires-Python: >=3.9
Requires-Dist: jinja2>=3.0
